disdat_kfp/__init__.py
disdat_kfp/cache_check.py
disdat_kfp/cache_push.py
disdat_kfp/caching_wrapper.py
disdat_kfp/gather_data.py
disdat_kfp/version.py
disdat_kfp-0.1.dev22.dist-info/LICENSE
disdat_kfp-0.1.dev22.dist-info/METADATA
disdat_kfp-0.1.dev22.dist-info/WHEEL
disdat_kfp-0.1.dev22.dist-info/top_level.txt
disdat_kfp-0.1.dev22.dist-info/RECORD
