Metadata-Version: 2.1
Name: disdat-kfp
Version: 0.1.dev22
Summary: UNKNOWN
Home-page: https://github.com/kyocum/disdat-kfp
Author: Ken Yocum, Zixuan Zhang
Author-email: kyocum@gmail.com, zz2777@columbia.edu
License: Apache License, version 2.0
Platform: UNKNOWN
Classifier: Development Status :: 4 - Beta
Classifier: Intended Audience :: Science/Research
Classifier: Topic :: Scientific/Engineering
Classifier: License :: OSI Approved :: Apache Software License
Classifier: Programming Language :: Python :: 3.8
Classifier: Operating System :: OS Independent
Classifier: Natural Language :: English
License-File: LICENSE
Requires-Dist: disdat (>=0.9.16)
Requires-Dist: kfp (==1.6.5)
Provides-Extra: dev
Requires-Dist: pytest ; extra == 'dev'
Requires-Dist: ipython ; extra == 'dev'
Requires-Dist: pytest-xdist ; extra == 'dev'
Requires-Dist: twine ; extra == 'dev'
Requires-Dist: build ; extra == 'dev'
